wizardhtml/__init__.py
wizardhtml/wizard_html.py
wizardhtml/utils/__init__.py
wizardhtml/utils/wildcard.py
wizardhtml/utils/tw_html_parser/__init__.py
wizardhtml/utils/tw_html_parser/_utils.py
wizardhtml/utils/tw_html_parser/beautify_html.py
wizardhtml/utils/tw_html_parser/dom.py
wizardhtml/utils/tw_html_parser/entities_hash.c
wizardhtml/utils/tw_html_parser/entities_hash.h
wizardhtml/utils/tw_html_parser/entities_wrapper.cp311-win_amd64.pyd
wizardhtml/utils/tw_html_parser/entities_wrapper.pyx
wizardhtml/utils/tw_html_parser/error.py
wizardhtml/utils/tw_html_parser/html_to_md_dom.py
wizardhtml/utils/tw_html_parser/parser.py
wizardhtml/utils/tw_html_parser/serializer.py
wizardhtml/utils/tw_html_parser/serializer_pretty.py
wizardhtml/utils/tw_html_parser/tokenizer.py
wizardhtml/utils/tw_html_parser/tokens.py
wizardhtml/wizard_cleaners/__init__.py
wizardhtml/wizard_cleaners/tw_html_cleaner/__init__.py
wizardhtml/wizard_cleaners/tw_html_cleaner/constants.py
wizardhtml/wizard_cleaners/tw_html_cleaner/html_cleaner.py
wizardhtml-1.0.1.dist-info/licenses/LICENSE
wizardhtml-1.0.1.dist-info/METADATA
wizardhtml-1.0.1.dist-info/WHEEL
wizardhtml-1.0.1.dist-info/top_level.txt
wizardhtml-1.0.1.dist-info/RECORD
