Metadata-Version: 2.4
Name: wizardhtml
Version: 1.0.1
Summary: WHATWG-compliant HTML5 toolkit: DFA tokenizer, spec-guided tree builder, DOM, configurable serializer, high-level cleaner, pretty-printer, and HTML to Markdown.
Author-email: Mattia Rubino <textwizard.dev@gmail.com>
License: WizardHTML — Copyright (C) 2024–2025 Mattia Rubino
Project-URL: Homepage, https://github.com/textwizard-dev/wizardhtml
Project-URL: Source, https://github.com/textwizard-dev/wizardhtml
Project-URL: Documentation, https://wizardhtml.readthedocs.io/en/latest/
Keywords: html,html5,whatwg,html-parser,tokenizer,dfa,dom,tree-builder,serializer,pretty-printer,pretty-printing,formatter,cleaner,sanitizer,html-cleaning,html-to-markdown,markdown-converter,unicode,html-entities,rcdata,svg,mathml,fragment-parsing,dom-serialization
Classifier: Programming Language :: Python :: 3
Classifier: Programming Language :: Python :: 3.9
Classifier: Programming Language :: Python :: 3.10
Classifier: Programming Language :: Python :: 3.11
Classifier: Intended Audience :: Developers
Classifier: Topic :: Text Processing
Classifier: License :: OSI Approved :: GNU Affero General Public License v3 or later (AGPLv3+)
Requires-Python: >=3.9
License-File: LICENSE
Requires-Dist: marisa-trie>=1.3.0
Requires-Dist: pyahocorasick>=2.2.0
Dynamic: license-file
